routinemaker/__init__.py
routinemaker/exercises.py
routinemaker/prompt.py
routinemaker/routine.py
routinemaker/routinemaker.py
routinemaker/data/exercises.json
routinemaker-0.5.3.dist-info/LICENSE
routinemaker-0.5.3.dist-info/METADATA
routinemaker-0.5.3.dist-info/WHEEL
routinemaker-0.5.3.dist-info/entry_points.txt
routinemaker-0.5.3.dist-info/top_level.txt
routinemaker-0.5.3.dist-info/RECORD
