Metadata-Version: 2.1
Name: routinemaker
Version: 0.5.3
Summary: A Python CLI that generates strength, cardio, and HIIT exercise routines using parametric curves
Home-page: https://github.com/kathyqian/routinemaker
Author: Kathy Qian
Author-email: hello@kathyqian.com
License: MIT
Platform: UNKNOWN
Classifier: Programming Language :: Python :: 3
Classifier: License :: OSI Approved :: MIT License
Classifier: Operating System :: OS Independent
Requires-Dist: click
Requires-Dist: pyfiglet
Requires-Dist: XlsxWriter
Requires-Dist: numpy
Requires-Dist: setuptools
